bedrock_be/.gitignore
bedrock_be/README.md
bedrock_be/__init__.py
bedrock_be/__main__.py
bedrock_be/log.py
bedrock_be/settings.py
bedrock_be/db/.env
bedrock_be/db/base.py
bedrock_be/db/dependencies.py
bedrock_be/db/main.py
bedrock_be/db/meta.py
bedrock_be/db/utils.py
bedrock_be/db/models/__init__.py
bedrock_be/db/models/schemas.py
bedrock_be/deploy/docker-compose.dev.yml
bedrock_be/services/__init__.py
bedrock_be/services/redis/__init__.py
bedrock_be/services/redis/dependency.py
bedrock_be/services/redis/lifespan.py
bedrock_be/tests/__init__.py
bedrock_be/tests/conftest.py
bedrock_be/tests/test_bedrock_be.py
bedrock_be/web/__init__.py
bedrock_be/web/application.py
bedrock_be/web/lifespan.py
bedrock_be/web/api/__init__.py
bedrock_be/web/api/router.py
bedrock_be/web/api/monitoring/__init__.py
bedrock_be/web/api/monitoring/views.py
bedrock_llm/__init__.py
bedrock_llm/agent.py
bedrock_llm/aws_clients.py
bedrock_llm/__pycache__/__init__.cpython-311.pyc
bedrock_llm/__pycache__/agent.cpython-311.pyc
bedrock_llm/__pycache__/aws_clients.cpython-311.pyc
bedrock_llm/__pycache__/client.cpython-311.pyc
bedrock_llm/client/__init__.py
bedrock_llm/client/async_client.py
bedrock_llm/client/base.py
bedrock_llm/client/embeddings.py
bedrock_llm/client/reranking.py
bedrock_llm/client/sync_client.py
bedrock_llm/client/__pycache__/__init__.cpython-311.pyc
bedrock_llm/client/__pycache__/async_client.cpython-311.pyc
bedrock_llm/client/__pycache__/base.cpython-311.pyc
bedrock_llm/client/__pycache__/embeddings.cpython-311.pyc
bedrock_llm/client/__pycache__/sync_client.cpython-311.pyc
bedrock_llm/config/__init__.py
bedrock_llm/config/base.py
bedrock_llm/config/model.py
bedrock_llm/config/__pycache__/__init__.cpython-311.pyc
bedrock_llm/config/__pycache__/base.cpython-311.pyc
bedrock_llm/config/__pycache__/model.cpython-311.pyc
bedrock_llm/models/__init__.py
bedrock_llm/models/ai21.py
bedrock_llm/models/amazon.py
bedrock_llm/models/anthropic.py
bedrock_llm/models/base.py
bedrock_llm-0.1.8.5.dist-info/LICENSE
bedrock_llm-0.1.8.5.dist-info/METADATA
bedrock_llm-0.1.8.5.dist-info/WHEEL
bedrock_llm-0.1.8.5.dist-info/top_level.txt
bedrock_llm-0.1.8.5.dist-info/RECORD
