Metadata-Version: 2.1
Name: bedrock_llm
Version: 0.1.8.5
Summary: A Python LLM framework for interacting with AWS Bedrock services, built on top of boto3. This library serves as a comprehensive tool for fast prototyping, building POCs, and deploying production-ready LLM applications with robust infrastructure support.
Home-page: https://github.com/Phicks-debug/bedrock_llm
Author: Tran Quy An
Author-email: an.tq@techxcorp.com
Keywords: aws bedrock llm machine-learning ai
Classifier: Development Status :: 3 - Alpha
Classifier: Intended Audience :: Developers
Classifier: License :: OSI Approved :: MIT License
Classifier: Operating System :: OS Independent
Classifier: Programming Language :: Python :: 3
Classifier: Programming Language :: Python :: 3.9
Classifier: Programming Language :: Python :: 3.10
Requires-Python: >=3.9
License-File: LICENSE
Requires-Dist: pydantic>=2.0.0
Requires-Dist: boto3>=1.18.0
Requires-Dist: botocore>=1.21.0
Requires-Dist: aiobotocore>=2.15.2
Requires-Dist: jinja2>=3.1.2
Requires-Dist: psutil>=5.9.0
Requires-Dist: pytz>=2023.3
Requires-Dist: termcolor>=2.3.0
Requires-Dist: databases[postgresql]>=0.7.0
Requires-Dist: sqlalchemy>=2.0.0
Requires-Dist: asyncpg>=0.27.0
Requires-Dist: types-redis>=4.6.0
Requires-Dist: types-pytz
Requires-Dist: rx==3.2.0
